wizwad/__init__.py
wizwad/__main__.py
wizwad/wad.py
wizwad-0.4.4.dist-info/LICENSE
wizwad-0.4.4.dist-info/METADATA
wizwad-0.4.4.dist-info/WHEEL
wizwad-0.4.4.dist-info/entry_points.txt
wizwad-0.4.4.dist-info/RECORD
