Metadata-Version: 2.1
Name: wizwad
Version: 0.4.4
Summary: 
Home-page: https://github.com/StarrFox/wizwad
License: MIT
Author: StarrFox
Author-email: starrfox6312@gmail.com
Requires-Python: >=3.10,<4.0
Classifier: License :: OSI Approved :: MIT License
Classifier: Programming Language :: Python :: 3
Classifier: Programming Language :: Python :: 3.10
Classifier: Programming Language :: Python :: 3.11
Classifier: Programming Language :: Python :: 3.12
Requires-Dist: click (>=8.1.7,<9.0.0)
Requires-Dist: more-itertools (>=10.1.0,<11.0.0)
Project-URL: Repository, https://github.com/StarrFox/wizwad
